too/__init__.py
too/__main__.py
too/carton.py
too/database.py
too/datamodel.py
too/dump.py
too/exceptions.py
too/mock.py
too/tools.py
too/validate.py
too/xmatch.py
sdss_too-1.1.1.dist-info/METADATA
sdss_too-1.1.1.dist-info/WHEEL
sdss_too-1.1.1.dist-info/entry_points.txt
sdss_too-1.1.1.dist-info/licenses/LICENSE.md
sdss_too-1.1.1.dist-info/RECORD
