Metadata-Version: 2.4
Name: sdss-too
Version: 1.1.1
Summary: Targets of Opportunity (ToO) for SDSS-V
Project-URL: Homepage, https://github.com/sdss/too
Project-URL: Repository, https://github.com/sdss/too
Project-URL: Documentation, https://sdss-too.readthedocs.org
Author-email: José Sánchez-Gallego <gallegoj@uw.edu>
License: BSD-3-Clause
License-File: LICENSE.md
Requires-Python: <3.13,>=3.12
Requires-Dist: adbc-driver-postgresql>=1.2.0
Requires-Dist: astropy-healpix>=1.0.2
Requires-Dist: astropy>=7.0.0
Requires-Dist: httpx>=0.27.0
Requires-Dist: polars>=1.17.1
Requires-Dist: pyarrow>=18.0.0
Requires-Dist: rich>=13.7.0
Requires-Dist: sdss-coordio>=1.13.0
Requires-Dist: sdss-target-selection>=1.4.3
Requires-Dist: sdssdb>=0.13.3
Requires-Dist: sdsstools>=1.8.2
Requires-Dist: typer>=0.13.0
Provides-Extra: lts
Requires-Dist: polars-lts-cpu>=1.17.1; extra == 'lts'
